[
  {
    "comprehension": null,
    "direction": null,
    "content": "<p>The results of a consolidated drained triaxial test on a normally consolidated clay are shown in the figure. The angle of internal friction is</p>\n<img src=\"https://app-content.cdn.examgoal.net/fly/@width/image/jaoe38c1mbhyjf23/d552f654-198b-4f78-b037-2b77884c66e9/2e340cb0-4144-11f0-b425-4d40a5be1093/file-jaoe38c1mbhyjf24.png?format=png\" data-orsrc=\"https://app-content.cdn.examgoal.net/image/jaoe38c1mbhyjf23/d552f654-198b-4f78-b037-2b77884c66e9/2e340cb0-4144-11f0-b425-4d40a5be1093/file-jaoe38c1mbhyjf24.png\" loading=\"lazy\" style=\"max-width:100%;height:auto;display:block;margin:0 auto;max-height:40vh;vertical-align:baseline\" alt=\"GATE CE 2025 Set 1 Geotechnical Engineering - Shear Strength of Soil Question 1 English\">",
    "options": [
      {
        "identifier": "A",
        "content": " $\\sin ^{-1}\\left(\\frac{1}{2}\\right)$\n"
      },
      {
        "identifier": "B",
        "content": "$\\sin ^{-1}\\left(\\frac{1}{3}\\right)$\n"
      },
      {
        "identifier": "C",
        "content": " $\\sin ^{-1}\\left(\\frac{2}{3}\\right)$\n"
      },
      {
        "identifier": "D",
        "content": " $\\sin ^{-1}\\left(\\frac{3}{4}\\right)$"
      }
    ],
    "correct_options": [
      "B"
    ],
    "answer": null,
    "explanation": "<p>For a consolidated drained (CD) triaxial test on a normally consolidated clay, the cohesion ($C$) is zero. The principal stresses are related to the angle of internal friction ($\\phi$) through the following equation:</p>\n<p>$ \\sigma_1 = \\sigma_3 \\tan^2\\left(45^\\circ + \\frac{\\phi}{2}\\right) $</p>\n<p>Substituting the given values:</p>\n<p>$ 100 = 50 \\times \\left[\\frac{1+\\sin \\phi}{1-\\sin \\phi}\\right] $</p>\n<p>This simplifies to:</p>\n<p>$ 100 = 50 \\left(\\frac{1 + \\sin \\phi}{1 - \\sin \\phi}\\right) $</p>\n<p>Solving for $\\sin \\phi$, we find:</p>\n<p>$ \\sin \\phi = \\frac{1}{3} $</p>\n<p>Thus, the angle of internal friction $\\phi$ is:</p>\n<p>$ \\phi = \\sin^{-1}\\left(\\frac{1}{3}\\right) $</p>",
    "topic": null,
    "year": 2025,
    "yearKey": "gate-ce-2025-set-1",
    "difficulty": null
  },
  {
    "direction": null,
    "comprehension": null,
    "content": "An unconfined compression strength test was conducted on a cohesive soil. The test specimen failed at an axial stress of 76 kPa. The undrained cohesion (in kPa, in integer) of the soil is _____",
    "options": [],
    "correct_options": [],
    "explanation": "<p>Given: Axial stress $\\sigma_1 = 76 \\text{kPa}$ and $\\sigma_3 = 0$ (since this is an unconfined compression strength test).</p>\n\n<p>We need to find the cohesion, denoted as $C$. The formula is:</p>\n\n<p>\n\n<p>$$\\sigma_1 = \\sigma_3 \\tan^2\\left(45 + \\frac{\\phi}{2}\\right) + 2C \\tan\\left(45 + \\frac{\\phi}{2}\\right)$$</p>\n\n</p>\n\n<p>In this case, $\\sigma_3 = 0$ and the internal angle of friction $\\phi = 0$.</p>\n\n<p>Thus, the equation simplifies to:</p>\n\n<p>\n\n<p>$$\\sigma_1 = 2C$$</p>\n\n</p>\n\n<p>Substituting the given value of $\\sigma_1 = 76 \\text{kPa}$:</p>\n\n<p>\n\n<p>$$\\begin{array}{ll} \\sigma_1 = 2C & \\Rightarrow 76 = 2C \\\\\\\\ \\text{Therefore,} & C = \\frac{76}{2} \\\\\\\\ & C = 38 \\text{kPa} \\end{array}$$</p>\n\n</p>\n\n<p>Hence, the undrained cohesion of the soil is 38 kPa.</p>",
    "answer": "38",
    "topic": null,
    "year": 2023,
    "yearKey": "gate-ce-2023-set-2",
    "difficulty": null
  },
  {
    "direction": null,
    "comprehension": null,
    "content": "<span style=\"\">A drained direct shear test was carried out on a sandy soil. Under a normal stress of 50 kPa, the test specimen failed at a shear stress of 35 kPa. The angle of internal friction of the sample is ________ degree (round off to the nearest integer).</span>",
    "options": [],
    "correct_options": [],
    "explanation": "<p>Given the following values in the drained shear test :</p>\n\n<ul>\n\n<li>Normal stress, $\\sigma_n = 50$ kPa</li>\n\n<li>Shear stress, $\\tau_f = 35$ kPa</li>\n\n<li>Cohesion, $C = 0$ (since the soil is sand)</li>\n\n</ul>\n\n<p>The angle of internal friction, $\\phi$, can be found using the formula :</p>\n\n<p>$$\\tau_f = \\sigma_n \\tan \\phi + C$$</p>\n\n<p>Since $C = 0$, the equation simplifies to :</p>\n\n<p>$$\\tau_f = \\sigma_n \\tan \\phi$$</p>\n\n<p>Substituting the given values :</p>\n\n<p>$$\\frac{35}{50} = \\tan \\phi$$</p>\n\n<p>Hence :</p>\n\n<p>$$\\phi = \\tan^{-1}\\left(\\frac{35}{50}\\right) \\approx 34.99^\\circ$$</p>\n\n<p>Rounding to the nearest integer, the angle of internal friction, $\\phi$, is 35 degrees.</p>",
    "answer": "35",
    "topic": null,
    "year": 2023,
    "yearKey": "gate-ce-2023-set-1",
    "difficulty": null
  },
  {
    "direction": null,
    "content": "<p>Match the following in Column X with Column Y :</p>\n<p><table>\n<thead>\n  <tr>\n    <th></th>\n    <th>Column X</th>\n    <th></th>\n    <th>Column Y</th>\n  </tr>\n</thead>\n<tbody>\n  <tr>\n    <td>P.</td>\n    <td>In a triaxial compression test, with increase of axial strain in loose sand under drained shear condition. The volumetric strain.</td>\n    <td>I.</td>\n    <td>decreases</td>\n  </tr>\n  <tr>\n    <td>Q.</td>\n    <td>In a triaxial compression test, with increase of axial strain in loose sand under undrained shear condition, the excess pore water pressure.</td>\n    <td>II.</td>\n    <td>increase</td>\n  </tr>\n  <tr>\n    <td>R.</td>\n    <td>In a triaxial compression test, the pore pressure parameter \"B\" for a saturated soil.</td>\n    <td>III.</td>\n    <td>remains same</td>\n  </tr>\n  <tr>\n    <td>S.</td>\n    <td>For shallow strip footing in pure saturated clay, Terzaghi's bearing capacity factor (N$$_q$$) due to surcharge.</td>\n    <td>IV.</td>\n    <td>is always 0.0</td>\n  </tr>\n  <tr>\n    <td></td>\n    <td></td>\n    <td>V.</td>\n    <td>is always 1.0</td>\n  </tr>\n  <tr>\n    <td></td>\n    <td></td>\n    <td>VI.</td>\n    <td>is always 0.5</td>\n  </tr>\n</tbody>\n</table></p>\n<p>Which one of the following combinations is correct?</p>",
    "options": [
      {
        "identifier": "A",
        "content": "(P)-(I), (Q)-(II), (R)-(V), (S)-(VI)"
      },
      {
        "identifier": "B",
        "content": "(P)-(I), (Q)-(III), (R)-(VI), (S)-(IV)"
      },
      {
        "identifier": "C",
        "content": "(P)-(I), (Q)-(I), (R)-(IV), (S)-(V)"
      },
      {
        "identifier": "D",
        "content": "(P)-(I), (Q)-(II), (R)-(V), (S)-(V)"
      }
    ],
    "correct_options": [
      "D"
    ],
    "answer": null,
    "explanation": "<p>(P) <img src=\"https://app-content.cdn.examgoal.net/fly/@width/image/jaoe38c1m0lcw5oi/fcbafb26-caa9-4fa8-a786-2f2e649f5fcb/49111a20-695c-11ef-9436-af3b89bbb46b/file-jaoe38c1m0lcw5oj.png?format=png\" data-orsrc=\"https://app-content.cdn.examgoal.net/image/jaoe38c1m0lcw5oi/fcbafb26-caa9-4fa8-a786-2f2e649f5fcb/49111a20-695c-11ef-9436-af3b89bbb46b/file-jaoe38c1m0lcw5oj.png\" loading=\"lazy\" style=\"max-width:100%;height:auto;display:block;margin:0 auto;max-height:40vh;vertical-align:baseline\" alt=\"GATE CE 2022 Set 2 Geotechnical Engineering - Shear Strength of Soil Question 6 English Explanation 1\"></p>\n<p>(Q) <img src=\"https://app-content.cdn.examgoal.net/fly/@width/image/jaoe38c1m0lcw2b2/3e268f8f-1896-4872-a1b3-f5d13e100d59/4675fce0-695c-11ef-9436-af3b89bbb46b/file-jaoe38c1m0lcw2b3.png?format=png\" data-orsrc=\"https://app-content.cdn.examgoal.net/image/jaoe38c1m0lcw2b2/3e268f8f-1896-4872-a1b3-f5d13e100d59/4675fce0-695c-11ef-9436-af3b89bbb46b/file-jaoe38c1m0lcw2b3.png\" loading=\"lazy\" style=\"max-width:100%;height:auto;display:block;margin:0 auto;max-height:40vh;vertical-align:baseline\" alt=\"GATE CE 2022 Set 2 Geotechnical Engineering - Shear Strength of Soil Question 6 English Explanation 2\"></p>\n<p>(R) Skempton parameter B value for saturated cohesive soil is 1.</p>\n<p>(S) For clay, N<sub>q</sub> = 1, N<sub>c</sub> = 5.7 and N<sub>r</sub> = 0 ($$\\because$$ $$\\phi$$ = 0)</p>",
    "topic": null,
    "year": 2022,
    "yearKey": "gate-ce-2022-set-2",
    "difficulty": null
  },
  {
    "comprehension": null,
    "direction": null,
    "content": "<p>In the context of shear strength of soil, which of the following statements is/are CORRECT?</p>",
    "options": [
      {
        "identifier": "A",
        "content": "The unconfined compression test is a special case of the unconsolidated-undrained (UU) triaxial tests.\n"
      },
      {
        "identifier": "B",
        "content": "The shear strength parameters obtained from the consolidated-drained (CD) triaxial tests should be used to analyse rapid construction in clay.\n"
      },
      {
        "identifier": "C",
        "content": "Vane shear test is commonly used for determining in situ undrained strength of saturated clay soils.\n"
      },
      {
        "identifier": "D",
        "content": "In an unconsolidated-undrained (UU) triaxial tests, the angle of internal friction ( $\\phi$ ) is equal to zero."
      }
    ],
    "correct_options": [
      "A",
      "C",
      "D"
    ],
    "answer": null,
    "explanation": "<p>In the context of shear strength of soil :</p>\n<p>(A) The unconfined compression test is a special case of the unconsolidatedundrained (UU) triaxial test. (Correct)</p>\n<p><p>The unconfined compression test (UCT) is essentially a UU triaxial test conducted without confining pressure ( $\\sigma_3=0$ ).</p></p>\n<p><p>Since it does not allow drainage, it is a special case of the UU test.</p></p>\n<p>(B) The shear strength parameters obtained from the consolidated-drained (CD) triaxial test should be used to analyze rapid construction in clay. (Incorrect)</p>\n<p>CD tests allow full consolidation and drainage, representing long-term stability.</p>\n\n<p>Rapid construction does not allow drainage, so an unconsolidatedundrained (UU) test is more appropriate.</p>\n\n<p>(C) Vane shear test is commonly used for determining in situ undrained strength of saturated clay soils. (Correct)</p>\n\n<p><p>The vane shear test is used for soft, saturated clays, where the undrained shear strength is crucial.</p></p>\n<p><p>It directly measures shear strength without requiring drainage.</p></p>\n\n<p>(D) In an unconsolidated-undrained (UU) triaxial test, the angle of internal friction $(\\phi)$ is equal to zero. (Correct)</p>\n\n<p><p>In the UU test, soil is not allowed to consolidate, and failure happens due to undrained shear strength (cu).</p></p>\n<p><p>The total stress parameters in the UU test give $\\phi=0$ because the strength is only from cohesion (c).</p></p>\n\n<p>Hence, the correct options are (A), (C) and (D).</p>",
    "topic": null,
    "year": 2025,
    "yearKey": "gate-ce-2025-set-2",
    "difficulty": null
  },
  {
    "direction": null,
    "comprehension": null,
    "content": "<p>In the given figure, Point O indicates the stress point of a soil element at initial non-hydrostatic stress condition. For the stress path (OP), which of the following loading conditions is correct?</p>\n\n<img src=\"https://app-content.cdn.examgoal.net/fly/@width/image/jaoe38c1lz8x4w89/8ccf70ff-f66d-48ad-8229-24af056c160a/0acf5190-4eb9-11ef-9888-754dd0e4e8db/file-jaoe38c1lz8x4w8a.png?format=png\" data-orsrc=\"https://app-content.cdn.examgoal.net/image/jaoe38c1lz8x4w89/8ccf70ff-f66d-48ad-8229-24af056c160a/0acf5190-4eb9-11ef-9888-754dd0e4e8db/file-jaoe38c1lz8x4w8a.png\" loading=\"lazy\" style=\"max-width:100%;height:auto;display:block;margin:0 auto;max-height:40vh;vertical-align:baseline\" alt=\"GATE CE 2023 Set 2 Geotechnical Engineering - Shear Strength of Soil Question 3 English\">\n",
    "options": [
      {
        "identifier": "A",
        "content": "𝜎<sub>𝑣</sub> is increasing and 𝜎<sub>ℎ</sub> is constant"
      },
      {
        "identifier": "B",
        "content": "𝜎<sub>𝑣</sub> is constant and 𝜎<sub>ℎ</sub> is increasing"
      },
      {
        "identifier": "C",
        "content": "𝜎<sub>𝑣</sub> is increasing and 𝜎<sub>ℎ</sub> is decreasing"
      },
      {
        "identifier": "D",
        "content": "𝜎<sub>𝑣</sub> is decreasing and 𝜎<sub>ℎ</sub> is increasing"
      }
    ],
    "correct_options": [
      "A"
    ],
    "explanation": "<img src=\"https://app-content.cdn.examgoal.net/fly/@width/image/jaoe38c1lz8x8kbj/9b05ef01-a132-4647-95b8-702fb6ba7403/70d8d6f0-4eb9-11ef-9888-754dd0e4e8db/file-jaoe38c1lz8x8kbk.png?format=png\" data-orsrc=\"https://app-content.cdn.examgoal.net/image/jaoe38c1lz8x8kbj/9b05ef01-a132-4647-95b8-702fb6ba7403/70d8d6f0-4eb9-11ef-9888-754dd0e4e8db/file-jaoe38c1lz8x8kbk.png\" loading=\"lazy\" style=\"max-width:100%;height:auto;display:block;margin:0 auto;max-height:40vh;vertical-align:baseline\" alt=\"GATE CE 2023 Set 2 Geotechnical Engineering - Shear Strength of Soil Question 3 English Explanation\">\n\n<p>We analyze the stress path by considering :</p>\n\n<ul>\n<li>$\\sigma_v$ : Major principal stress</li><br>\n<li>$\\sigma_h$ : Minor principal stress</li>\n</ul>\n<p>Given that the slope is $1:1$, we have :</p>\n\n<p>$$ \\begin{aligned}  &amp; \\therefore \\frac{d q}{d p}=1 \\\\\\\\ &amp; \\frac{d \\sigma_v - d \\sigma_h}{d \\sigma_v + d \\sigma_h}=1 \\\\\\\\ &amp; d \\sigma_h=0  \\end{aligned} $$</p>\n\n<p>This indicates that $\\sigma_h$ remains constant while $\\sigma_v$ increases.</p>\n\n<p>Hence, the correct loading condition is :</p>\n\n<ul>\n<li>$\\sigma_v$ is increasing</li><br>\n<li>$\\sigma_h$ is constant</li>\n</ul>\n<p>The correct option is (A).</p>",
    "answer": null,
    "topic": null,
    "year": 2023,
    "yearKey": "gate-ce-2023-set-2",
    "difficulty": null
  }
]