[
  {
    "comprehension": null,
    "direction": null,
    "content": "<p>Animal of which phylum have hooks and\nsuckers and are endoparasite on other animals?</p>",
    "options": [
      {
        "identifier": "A",
        "content": "Platyhelminthes"
      },
      {
        "identifier": "B",
        "content": "Annelida"
      },
      {
        "identifier": "C",
        "content": "Aschelminthes"
      },
      {
        "identifier": "D",
        "content": "Arthropoda"
      }
    ],
    "correct_options": [
      "A"
    ],
    "answer": null,
    "explanation": "<p>Animals of phylum–Platyhelminthes have\nhooks and suckers and are endoparasite of other\nanimals.</p>\n<p>These are triploblastic, bilaterally symmetrical,\nacoelomate animals with blind sac body plan. They\nlive as endoparasites in intestine of other animals.\nFor this purpose, they bear hooks or suckers near\ntheir mouth region which help them to cling on\nthe intestinal walls of the host and obtain\nnutrition.</p>\n<p>Aschelminthes (roundworm) show organ level\nof symmetry and are triploblastic and\npseudocoelomate.</p>\n<p>Annelids are bilaterally symmetrical,\ntriploblastic and coelomate animals.</p>\n<p>Arthropods These are bilaterally symmetrical,\ntriploblastic segmented, coelomate animals.</p>",
    "topic": null,
    "year": 2019,
    "yearKey": "aiims-2019",
    "difficulty": null
  },
  {
    "comprehension": null,
    "direction": null,
    "content": "<p>Assertion Taenia solium and Dugesia belong\nto Platyhelminthes.</p>\n<p>Reason : Platyhelminthes are coelomates.</p>",
    "options": [
      {
        "identifier": "A",
        "content": "Both A and R are true and R is the correct explanation of A\n"
      },
      {
        "identifier": "B",
        "content": "Both A and R are true, but R is not the correct explanation of A\n"
      },
      {
        "identifier": "C",
        "content": "A is true, but R is false\n"
      },
      {
        "identifier": "D",
        "content": "A and R are false\n"
      }
    ],
    "correct_options": [
      "C"
    ],
    "answer": null,
    "explanation": "<p>Taenia solium belongs to the class – Cestoda\nand Dugesia (Planaria) belongs to Turbellaria class\nof Platyhelminthes. These are acoelomates, i.e.\nthey do not possess any fluid-filled cavity.</p>",
    "topic": null,
    "year": 2018,
    "yearKey": "aiims-2018",
    "difficulty": null
  }
]